[
  {
    "httpRequest": {
      "path": "/api/information-items",
      "queryStringParameters": {
        "searchPattern": "abc"
      }
    },
    "httpResponse": {
      "headers": {
        "Content-Type": ["application/json"]
      },
      "body": "{\"errorMessage\":\"\",\"items\":[{\"_id\":\"5f95f8ef94bbe7e5201ce0e8\",\"ean\":\"5060146468602\",\"correspondingInformationItems\":[{\"itemId\":\"amazon.de-B07XB2NKVZ\",\"link\":\"https://amazon.de/dp/B07XB2NKVZ\",\"price-current\":30.99,\"price-initial\":30.99,\"title-image\":\"https://images-na.ssl-images-amazon.com/images/I/51bQ3F9tPUL._SY679_.jpg\"}],\"title\":\"IntoThe Dead 2\",\"title-image\":\"https://images-na.ssl-images-amazon.com/images/I/51bQ3F9tPUL._SY679_.jpg\",\"navigationPath\":[\"MULTIMEDIA\",\"MULTIMEDIA_GAMES\",\"MULTIMEDIA_GAMES_NINTENDO_SWITCH\"],\"itemId\":\"MULTIMEDIA-MULTIMEDIA_GAMES-MULTIMEDIA_GAMES_NINTENDO_SWITCH-5060146468602\"},{\"_id\":\"5f95f8fb94bbe7e5201ce0f3\",\"ean\":\"5026555067959\",\"correspondingInformationItems\":[{\"itemId\":\"otto.de-1138852934\",\"link\":\"https://otto.de/p/1138852934\",\"price-current\":39,\"price-initial\":49.99,\"title-image\":\"https://i.otto.de/i/otto/4cb42887-b59f-5ef7-972b-462a29b0abb6?h=520&w=551&sm=clamp\"}],\"title\":\"BioShock- The Collection Nintendo Switch\",\"title-image\":\"https://i.otto.de/i/otto/4cb42887-b59f-5ef7-972b-462a29b0abb6?h=520&w=551&sm=clamp\",\"navigationPath\":[\"MULTIMEDIA\",\"MULTIMEDIA_GAMES\",\"MULTIMEDIA_GAMES_NINTENDO_SWITCH\"],\"itemId\":\"MULTIMEDIA-MULTIMEDIA_GAMES-MULTIMEDIA_GAMES_NINTENDO_SWITCH-5026555067959\"},{\"_id\":\"5f95f91294bbe7e5201ce0fe\",\"ean\":\"4012160121378\",\"correspondingInformationItems\":[{\"itemId\":\"otto.de-1023634643\",\"link\":\"https://otto.de/p/1023634643\",\"price-current\":29.24,\"price-initial\":29.24,\"title-image\":\"https://i.otto.de/i/otto/36625114?h=520&w=551&sm=clamp\"},{\"itemId\":\"amazon.de-B081SJVX8S\",\"link\":\"https://amazon.de/dp/B081SJVX8S\",\"title-image\":\"https://images-na.ssl-images-amazon.com/images/I/51jSiv6QLRL._AC_.jpg\"}],\"title\":\"LITTLENIGHTMARES COMPLETE EDITION Nintendo Switch, Software Pyramide\",\"title-image\":\"https://i.otto.de/i/otto/36625114?h=520&w=551&sm=clamp\",\"navigationPath\":[\"MULTIMEDIA\",\"MULTIMEDIA_GAMES\",\"MULTIMEDIA_GAMES_NINTENDO_SWITCH\"],\"itemId\":\"MULTIMEDIA-MULTIMEDIA_GAMES-MULTIMEDIA_GAMES_NINTENDO_SWITCH-4012160121378\"},{\"_id\":\"5f95f93c94bbe7e5201ce113\",\"ean\":\"4012160121576\",\"correspondingInformationItems\":[{\"itemId\":\"otto.de-1224264135\",\"link\":\"https://otto.de/p/1224264135\",\"price-current\":30,\"price-initial\":30,\"title-image\":\"https://i.otto.de/i/otto/6d31aff1-dc8b-5393-ae14-87c5317c273d?h=520&w=551&sm=clamp\"}],\"title\":\"AssassinsCreed 3 Remastered Nintendo Switch\",\"title-image\":\"https://i.otto.de/i/otto/6d31aff1-dc8b-5393-ae14-87c5317c273d?h=520&w=551&sm=clamp\",\"navigationPath\":[\"MULTIMEDIA\",\"MULTIMEDIA_GAMES\",\"MULTIMEDIA_GAMES_NINTENDO_SWITCH\"],\"itemId\":\"MULTIMEDIA-MULTIMEDIA_GAMES-MULTIMEDIA_GAMES_NINTENDO_SWITCH-4012160121576\"},{\"_id\":\"5f95f95e94bbe7e5201ce127\",\"ean\":\"5060146467292\",\"correspondingInformationItems\":[{\"itemId\":\"otto.de-893782212\",\"link\":\"https://otto.de/p/893782212\",\"price-current\":34.11,\"price-initial\":34.11,\"title-image\":\"https://i.otto.de/i/otto/33501188?h=520&w=551&sm=clamp\"},{\"itemId\":\"amazon.de-B07NMJK3GG\",\"link\":\"https://amazon.de/dp/B07NMJK3GG\",\"price-current\":34.99,\"price-initial\":34.99,\"title-image\":\"https://images-na.ssl-images-amazon.com/images/I/71x4%2B5KWCeL._SY679_.jpg\"}],\"title\":\"HollowKnight Nintendo Switch\",\"title-image\":\"https://i.otto.de/i/otto/33501188?h=520&w=551&sm=clamp\",\"navigationPath\":[\"MULTIMEDIA\",\"MULTIMEDIA_GAMES\",\"MULTIMEDIA_GAMES_NINTENDO_SWITCH\"],\"itemId\":\"MULTIMEDIA-MULTIMEDIA_GAMES-MULTIMEDIA_GAMES_NINTENDO_SWITCH-5060146467292\"},{\"_id\":\"5f95f98694bbe7e5201ce14f\",\"ean\":\"4260650740169\",\"correspondingInformationItems\":[{\"itemId\":\"otto.de-1236941713\",\"link\":\"https://otto.de/p/1236941713\",\"price-current\":29.99,\"price-initial\":29.99,\"title-image\":\"https://i.otto.de/i/otto/dac87319-f127-56ba-9651-1906c16ac674?h=520&w=551&sm=clamp\"}],\"title\":\"UmiharaKawase: BaZooKa! Nintendo Switch\",\"title-image\":\"https://i.otto.de/i/otto/dac87319-f127-56ba-9651-1906c16ac674?h=520&w=551&sm=clamp\",\"navigationPath\":[\"MULTIMEDIA\",\"MULTIMEDIA_GAMES\",\"MULTIMEDIA_GAMES_NINTENDO_SWITCH\"],\"itemId\":\"MULTIMEDIA-MULTIMEDIA_GAMES-MULTIMEDIA_GAMES_NINTENDO_SWITCH-4260650740169\"},{\"_id\":\"5f95f9a494bbe7e5201ce160\",\"ean\":\"4012160121040\",\"correspondingInformationItems\":[{\"itemId\":\"otto.de-785816872\",\"link\":\"https://otto.de/p/785816872\",\"price-current\":29.24,\"price-initial\":29.24,\"title-image\":\"https://i.otto.de/i/otto/30717060?h=520&w=551&sm=clamp\"},{\"itemId\":\"amazon.de-B0833VFSZW\",\"link\":\"https://amazon.de/dp/B0833VFSZW\",\"price-current\":15,\"price-initial\":15,\"title-image\":\"https://images-na.ssl-images-amazon.com/images/I/51NjtLmtR0L._SY679_.jpg\"}],\"title\":\"MeinGest端t - Ein Leben f端r die Pferde Nintendo Switch, Software Pyramide\",\"title-image\":\"https://i.otto.de/i/otto/30717060?h=520&w=551&sm=clamp\",\"navigationPath\":[\"MULTIMEDIA\",\"MULTIMEDIA_GAMES\",\"MULTIMEDIA_GAMES_NINTENDO_SWITCH\"],\"itemId\":\"MULTIMEDIA-MULTIMEDIA_GAMES-MULTIMEDIA_GAMES_NINTENDO_SWITCH-4012160121040\"},{\"_id\":\"5f95f9ff94bbe7e5201ce189\",\"ean\":\"8023171044811\",\"correspondingInformationItems\":[{\"itemId\":\"otto.de-1155475322\",\"link\":\"https://otto.de/p/1155475322\",\"price-current\":29.23,\"price-initial\":29.23,\"title-image\":\"https://i.otto.de/i/otto/a2312c29-e470-5082-8144-87aa0257ec20?h=520&w=551&sm=clamp\"}],\"title\":\"Journeyto the Savage Planet Nintendo Switch\",\"title-image\":\"https://i.otto.de/i/otto/a2312c29-e470-5082-8144-87aa0257ec20?h=520&w=551&sm=clamp\",\"navigationPath\":[\"MULTIMEDIA\",\"MULTIMEDIA_GAMES\",\"MULTIMEDIA_GAMES_NINTENDO_SWITCH\"],\"itemId\":\"MULTIMEDIA-MULTIMEDIA_GAMES-MULTIMEDIA_GAMES_NINTENDO_SWITCH-8023171044811\"},{\"_id\":\"5f95fa1594bbe7e5201ce194\",\"ean\":\"0045496421014\",\"correspondingInformationItems\":[{\"itemId\":\"otto.de-789083753\",\"link\":\"https://otto.de/p/789083753\",\"price-current\":53.08,\"price-initial\":53.08,\"title-image\":\"https://i.otto.de/i/otto/21472555?h=520&w=551&sm=clamp\"}],\"title\":\"XenobladeChronicles 2 Nintendo Switch\",\"title-image\":\"https://i.otto.de/i/otto/21472555?h=520&w=551&sm=clamp\",\"navigationPath\":[\"MULTIMEDIA\",\"MULTIMEDIA_GAMES\",\"MULTIMEDIA_GAMES_NINTENDO_SWITCH\"],\"itemId\":\"MULTIMEDIA-MULTIMEDIA_GAMES-MULTIMEDIA_GAMES_NINTENDO_SWITCH-0045496421014\"},{\"_id\":\"5f95fa3f94bbe7e5201ce1a5\",\"ean\":\"5026555067584\",\"correspondingInformationItems\":[{\"itemId\":\"otto.de-855196027\",\"link\":\"https://otto.de/p/855196027\",\"price-current\":46.92,\"price-initial\":46.92,\"title-image\":\"https://i.otto.de/i/otto/32391799?h=520&w=551&sm=clamp\"},{\"itemId\":\"amazon.de-B07HCBX8VZ\",\"link\":\"https://amazon.de/dp/B07HCBX8VZ\",\"price-current\":17.99,\"price-initial\":17.99,\"title-image\":\"https://images-na.ssl-images-amazon.com/images/I/81MKv47E7-L._SY679_.jpg\"}],\"title\":\"SidMeier's Civilization VI Nintendo Switch\",\"title-image\":\"https://i.otto.de/i/otto/32391799?h=520&w=551&sm=clamp\",\"navigationPath\":[\"MULTIMEDIA\",\"MULTIMEDIA_GAMES\",\"MULTIMEDIA_GAMES_NINTENDO_SWITCH\"],\"itemId\":\"MULTIMEDIA-MULTIMEDIA_GAMES-MULTIMEDIA_GAMES_NINTENDO_SWITCH-5026555067584\"},{\"_id\":\"5f95fa5994bbe7e5201ce1ba\",\"ean\":\"3760156485041\",\"correspondingInformationItems\":[{\"itemId\":\"otto.de-1179293312\",\"link\":\"https://otto.de/p/1179293312\",\"price-current\":49.99,\"price-initial\":49.99,\"title-image\":\"https://i.otto.de/i/otto/7171597f-9a32-5399-96ea-e25aab3e9c9c?h=520&w=551&sm=clamp\"}],\"title\":\"GearClub Unlimited 2: Tracks Edition Nintendo Switch\",\"title-image\":\"https://i.otto.de/i/otto/7171597f-9a32-5399-96ea-e25aab3e9c9c?h=520&w=551&sm=clamp\",\"navigationPath\":[\"MULTIMEDIA\",\"MULTIMEDIA_GAMES\",\"MULTIMEDIA_GAMES_NINTENDO_SWITCH\"],\"itemId\":\"MULTIMEDIA-MULTIMEDIA_GAMES-MULTIMEDIA_GAMES_NINTENDO_SWITCH-3760156485041\"},{\"_id\":\"5f95fa7b94bbe7e5201ce1c5\",\"ean\":\"4012160121101\",\"correspondingInformationItems\":[{\"itemId\":\"otto.de-785319485\",\"link\":\"https://otto.de/p/785319485\",\"price-current\":19.5,\"price-initial\":19.5,\"title-image\":\"https://i.otto.de/i/otto/30717151?h=520&w=551&sm=clamp\"}],\"title\":\"3DMini Golf Nintendo Switch, Software Pyramide\",\"title-image\":\"https://i.otto.de/i/otto/30717151?h=520&w=551&sm=clamp\",\"navigationPath\":[\"MULTIMEDIA\",\"MULTIMEDIA_GAMES\",\"MULTIMEDIA_GAMES_NINTENDO_SWITCH\"],\"itemId\":\"MULTIMEDIA-MULTIMEDIA_GAMES-MULTIMEDIA_GAMES_NINTENDO_SWITCH-4012160121101\"},{\"_id\":\"5f95fab794bbe7e5201ce1e1\",\"ean\":\"5060528034005\",\"correspondingInformationItems\":[{\"itemId\":\"otto.de-1195302943\",\"link\":\"https://otto.de/p/1195302943\",\"price-current\":39.99,\"price-initial\":39.99,\"title-image\":\"https://i.otto.de/i/otto/986f2b92-43e7-569f-a8d3-0155d6743d2b?h=520&w=551&sm=clamp\"}],\"title\":\"Ben10: Power Trip! Nintendo Switch\",\"title-image\":\"https://i.otto.de/i/otto/986f2b92-43e7-569f-a8d3-0155d6743d2b?h=520&w=551&sm=clamp\",\"navigationPath\":[\"MULTIMEDIA\",\"MULTIMEDIA_GAMES\",\"MULTIMEDIA_GAMES_NINTENDO_SWITCH\"],\"itemId\":\"MULTIMEDIA-MULTIMEDIA_GAMES-MULTIMEDIA_GAMES_NINTENDO_SWITCH-5060528034005\"},{\"_id\":\"5f95fad794bbe7e5201ce1f2\",\"ean\":\"0045496421175\",\"correspondingInformationItems\":[{\"itemId\":\"otto.de-789082145\",\"link\":\"https://otto.de/p/789082145\",\"price-current\":29,\"price-initial\":29,\"title-image\":\"https://i.otto.de/i/otto/21020441?h=520&w=551&sm=clamp\"}],\"title\":\"Snipperclips- Zusammen schneidet man am besten ab! Nintendo Switch\",\"title-image\":\"https://i.otto.de/i/otto/21020441?h=520&w=551&sm=clamp\",\"navigationPath\":[\"MULTIMEDIA\",\"MULTIMEDIA_GAMES\",\"MULTIMEDIA_GAMES_NINTENDO_SWITCH\"],\"itemId\":\"MULTIMEDIA-MULTIMEDIA_GAMES-MULTIMEDIA_GAMES_NINTENDO_SWITCH-0045496421175\"},{\"_id\":\"5f95fae894bbe7e5201ce20f\",\"ean\":\"0045496420383\",\"correspondingInformationItems\":[{\"itemId\":\"otto.de-789082480\",\"link\":\"https://otto.de/p/789082480\",\"price-current\":59,\"price-initial\":59,\"title-image\":\"https://i.otto.de/i/otto/23042987?h=520&w=551&sm=clamp\"},{\"itemId\":\"amazon.de-B01N4OZQWX\",\"link\":\"https://amazon.de/dp/B01N4OZQWX\",\"price-current\":49.99,\"price-initial\":49.99,\"title-image\":\"https://images-na.ssl-images-amazon.com/images/I/71Rqj%2BCh25L._SY679_.jpg\"}],\"title\":\"ARMSNintendo Switch\",\"title-image\":\"https://i.otto.de/i/otto/23042987?h=520&w=551&sm=clamp\",\"navigationPath\":[\"MULTIMEDIA\",\"MULTIMEDIA_GAMES\",\"MULTIMEDIA_GAMES_NINTENDO_SWITCH\"],\"itemId\":\"MULTIMEDIA-MULTIMEDIA_GAMES-MULTIMEDIA_GAMES_NINTENDO_SWITCH-0045496420383\"},{\"_id\":\"5f95fb0494bbe7e5201ce22a\",\"ean\":\"4260558699552\",\"correspondingInformationItems\":[{\"itemId\":\"otto.de-1096998438\",\"link\":\"https://otto.de/p/1096998438\",\"price-current\":38.98,\"price-initial\":38.98,\"title-image\":\"https://i.otto.de/i/otto/0351468a-21fc-5d0c-81c1-c73a5a9c2628?h=520&w=551&sm=clamp\"}],\"title\":\"BubbleBobble 4 Friends Nintendo Switch\",\"title-image\":\"https://i.otto.de/i/otto/0351468a-21fc-5d0c-81c1-c73a5a9c2628?h=520&w=551&sm=clamp\",\"navigationPath\":[\"MULTIMEDIA\",\"MULTIMEDIA_GAMES\",\"MULTIMEDIA_GAMES_NINTENDO_SWITCH\"],\"itemId\":\"MULTIMEDIA-MULTIMEDIA_GAMES-MULTIMEDIA_GAMES_NINTENDO_SWITCH-4260558699552\"}]}"
    }
  },
  {
    "httpRequest": {
      "path": "/api/wishlist-items",
      "queryStringParameters": {
        "searchPattern": "",
        "userId": "abc-123"
      }
    },
    "httpResponse": {
      "headers": {
        "Content-Type": ["application/json"]
      },
      "body": "{\"errorMessage\":\"\",\"items\":[{\"_id\":\"5f95f8ef94bbe7e5201ce0e8\",\"ean\":\"5060146468602\",\"correspondingInformationItems\":[{\"itemId\":\"amazon.de-B07XB2NKVZ\",\"link\":\"https://amazon.de/dp/B07XB2NKVZ\",\"price-current\":30.99,\"price-initial\":30.99,\"title-image\":\"https://images-na.ssl-images-amazon.com/images/I/51bQ3F9tPUL._SY679_.jpg\"}],\"title\":\"IntoThe Dead 2\",\"title-image\":\"https://images-na.ssl-images-amazon.com/images/I/51bQ3F9tPUL._SY679_.jpg\",\"navigationPath\":[\"MULTIMEDIA\",\"MULTIMEDIA_GAMES\",\"MULTIMEDIA_GAMES_NINTENDO_SWITCH\"],\"itemId\":\"MULTIMEDIA-MULTIMEDIA_GAMES-MULTIMEDIA_GAMES_NINTENDO_SWITCH-5060146468602\"},{\"_id\":\"5f95f91294bbe7e5201ce0fe\",\"ean\":\"4012160121378\",\"correspondingInformationItems\":[{\"itemId\":\"otto.de-1023634643\",\"link\":\"https://otto.de/p/1023634643\",\"price-current\":29.24,\"price-initial\":29.24,\"title-image\":\"https://i.otto.de/i/otto/36625114?h=520&w=551&sm=clamp\"},{\"itemId\":\"amazon.de-B081SJVX8S\",\"link\":\"https://amazon.de/dp/B081SJVX8S\",\"title-image\":\"https://images-na.ssl-images-amazon.com/images/I/51jSiv6QLRL._AC_.jpg\"}],\"title\":\"LITTLENIGHTMARES COMPLETE EDITION Nintendo Switch, Software Pyramide\",\"title-image\":\"https://i.otto.de/i/otto/36625114?h=520&w=551&sm=clamp\",\"navigationPath\":[\"MULTIMEDIA\",\"MULTIMEDIA_GAMES\",\"MULTIMEDIA_GAMES_NINTENDO_SWITCH\"],\"itemId\":\"MULTIMEDIA-MULTIMEDIA_GAMES-MULTIMEDIA_GAMES_NINTENDO_SWITCH-4012160121378\"},{\"_id\":\"5f95f93c94bbe7e5201ce113\",\"ean\":\"4012160121576\",\"correspondingInformationItems\":[{\"itemId\":\"otto.de-1224264135\",\"link\":\"https://otto.de/p/1224264135\",\"price-current\":30,\"price-initial\":30,\"title-image\":\"https://i.otto.de/i/otto/6d31aff1-dc8b-5393-ae14-87c5317c273d?h=520&w=551&sm=clamp\"}],\"title\":\"AssassinsCreed 3 Remastered Nintendo Switch\",\"title-image\":\"https://i.otto.de/i/otto/6d31aff1-dc8b-5393-ae14-87c5317c273d?h=520&w=551&sm=clamp\",\"navigationPath\":[\"MULTIMEDIA\",\"MULTIMEDIA_GAMES\",\"MULTIMEDIA_GAMES_NINTENDO_SWITCH\"],\"itemId\":\"MULTIMEDIA-MULTIMEDIA_GAMES-MULTIMEDIA_GAMES_NINTENDO_SWITCH-4012160121576\"},{\"_id\":\"5f95f95e94bbe7e5201ce127\",\"ean\":\"5060146467292\",\"correspondingInformationItems\":[{\"itemId\":\"otto.de-893782212\",\"link\":\"https://otto.de/p/893782212\",\"price-current\":34.11,\"price-initial\":34.11,\"title-image\":\"https://i.otto.de/i/otto/33501188?h=520&w=551&sm=clamp\"},{\"itemId\":\"amazon.de-B07NMJK3GG\",\"link\":\"https://amazon.de/dp/B07NMJK3GG\",\"price-current\":34.99,\"price-initial\":34.99,\"title-image\":\"https://images-na.ssl-images-amazon.com/images/I/71x4%2B5KWCeL._SY679_.jpg\"}],\"title\":\"HollowKnight Nintendo Switch\",\"title-image\":\"https://i.otto.de/i/otto/33501188?h=520&w=551&sm=clamp\",\"navigationPath\":[\"MULTIMEDIA\",\"MULTIMEDIA_GAMES\",\"MULTIMEDIA_GAMES_NINTENDO_SWITCH\"],\"itemId\":\"MULTIMEDIA-MULTIMEDIA_GAMES-MULTIMEDIA_GAMES_NINTENDO_SWITCH-5060146467292\"},{\"_id\":\"5f95f98694bbe7e5201ce14f\",\"ean\":\"4260650740169\",\"correspondingInformationItems\":[{\"itemId\":\"otto.de-1236941713\",\"link\":\"https://otto.de/p/1236941713\",\"price-current\":29.99,\"price-initial\":29.99,\"title-image\":\"https://i.otto.de/i/otto/dac87319-f127-56ba-9651-1906c16ac674?h=520&w=551&sm=clamp\"}],\"title\":\"UmiharaKawase: BaZooKa! Nintendo Switch\",\"title-image\":\"https://i.otto.de/i/otto/dac87319-f127-56ba-9651-1906c16ac674?h=520&w=551&sm=clamp\",\"navigationPath\":[\"MULTIMEDIA\",\"MULTIMEDIA_GAMES\",\"MULTIMEDIA_GAMES_NINTENDO_SWITCH\"],\"itemId\":\"MULTIMEDIA-MULTIMEDIA_GAMES-MULTIMEDIA_GAMES_NINTENDO_SWITCH-4260650740169\"},{\"_id\":\"5f95f9a494bbe7e5201ce160\",\"ean\":\"4012160121040\",\"correspondingInformationItems\":[{\"itemId\":\"otto.de-785816872\",\"link\":\"https://otto.de/p/785816872\",\"price-current\":29.24,\"price-initial\":29.24,\"title-image\":\"https://i.otto.de/i/otto/30717060?h=520&w=551&sm=clamp\"},{\"itemId\":\"amazon.de-B0833VFSZW\",\"link\":\"https://amazon.de/dp/B0833VFSZW\",\"price-current\":15,\"price-initial\":15,\"title-image\":\"https://images-na.ssl-images-amazon.com/images/I/51NjtLmtR0L._SY679_.jpg\"}],\"title\":\"MeinGest端t - Ein Leben f端r die Pferde Nintendo Switch, Software Pyramide\",\"title-image\":\"https://i.otto.de/i/otto/30717060?h=520&w=551&sm=clamp\",\"navigationPath\":[\"MULTIMEDIA\",\"MULTIMEDIA_GAMES\",\"MULTIMEDIA_GAMES_NINTENDO_SWITCH\"],\"itemId\":\"MULTIMEDIA-MULTIMEDIA_GAMES-MULTIMEDIA_GAMES_NINTENDO_SWITCH-4012160121040\"},{\"_id\":\"5f95f9ff94bbe7e5201ce189\",\"ean\":\"8023171044811\",\"correspondingInformationItems\":[{\"itemId\":\"otto.de-1155475322\",\"link\":\"https://otto.de/p/1155475322\",\"price-current\":29.23,\"price-initial\":29.23,\"title-image\":\"https://i.otto.de/i/otto/a2312c29-e470-5082-8144-87aa0257ec20?h=520&w=551&sm=clamp\"}],\"title\":\"Journeyto the Savage Planet Nintendo Switch\",\"title-image\":\"https://i.otto.de/i/otto/a2312c29-e470-5082-8144-87aa0257ec20?h=520&w=551&sm=clamp\",\"navigationPath\":[\"MULTIMEDIA\",\"MULTIMEDIA_GAMES\",\"MULTIMEDIA_GAMES_NINTENDO_SWITCH\"],\"itemId\":\"MULTIMEDIA-MULTIMEDIA_GAMES-MULTIMEDIA_GAMES_NINTENDO_SWITCH-8023171044811\"},{\"_id\":\"5f95fa1594bbe7e5201ce194\",\"ean\":\"0045496421014\",\"correspondingInformationItems\":[{\"itemId\":\"otto.de-789083753\",\"link\":\"https://otto.de/p/789083753\",\"price-current\":53.08,\"price-initial\":53.08,\"title-image\":\"https://i.otto.de/i/otto/21472555?h=520&w=551&sm=clamp\"}],\"title\":\"XenobladeChronicles 2 Nintendo Switch\",\"title-image\":\"https://i.otto.de/i/otto/21472555?h=520&w=551&sm=clamp\",\"navigationPath\":[\"MULTIMEDIA\",\"MULTIMEDIA_GAMES\",\"MULTIMEDIA_GAMES_NINTENDO_SWITCH\"],\"itemId\":\"MULTIMEDIA-MULTIMEDIA_GAMES-MULTIMEDIA_GAMES_NINTENDO_SWITCH-0045496421014\"},{\"_id\":\"5f95fa3f94bbe7e5201ce1a5\",\"ean\":\"5026555067584\",\"correspondingInformationItems\":[{\"itemId\":\"otto.de-855196027\",\"link\":\"https://otto.de/p/855196027\",\"price-current\":46.92,\"price-initial\":46.92,\"title-image\":\"https://i.otto.de/i/otto/32391799?h=520&w=551&sm=clamp\"},{\"itemId\":\"amazon.de-B07HCBX8VZ\",\"link\":\"https://amazon.de/dp/B07HCBX8VZ\",\"price-current\":17.99,\"price-initial\":17.99,\"title-image\":\"https://images-na.ssl-images-amazon.com/images/I/81MKv47E7-L._SY679_.jpg\"}],\"title\":\"SidMeier's Civilization VI Nintendo Switch\",\"title-image\":\"https://i.otto.de/i/otto/32391799?h=520&w=551&sm=clamp\",\"navigationPath\":[\"MULTIMEDIA\",\"MULTIMEDIA_GAMES\",\"MULTIMEDIA_GAMES_NINTENDO_SWITCH\"],\"itemId\":\"MULTIMEDIA-MULTIMEDIA_GAMES-MULTIMEDIA_GAMES_NINTENDO_SWITCH-5026555067584\"},{\"_id\":\"5f95fa5994bbe7e5201ce1ba\",\"ean\":\"3760156485041\",\"correspondingInformationItems\":[{\"itemId\":\"otto.de-1179293312\",\"link\":\"https://otto.de/p/1179293312\",\"price-current\":49.99,\"price-initial\":49.99,\"title-image\":\"https://i.otto.de/i/otto/7171597f-9a32-5399-96ea-e25aab3e9c9c?h=520&w=551&sm=clamp\"}],\"title\":\"GearClub Unlimited 2: Tracks Edition Nintendo Switch\",\"title-image\":\"https://i.otto.de/i/otto/7171597f-9a32-5399-96ea-e25aab3e9c9c?h=520&w=551&sm=clamp\",\"navigationPath\":[\"MULTIMEDIA\",\"MULTIMEDIA_GAMES\",\"MULTIMEDIA_GAMES_NINTENDO_SWITCH\"],\"itemId\":\"MULTIMEDIA-MULTIMEDIA_GAMES-MULTIMEDIA_GAMES_NINTENDO_SWITCH-3760156485041\"},{\"_id\":\"5f95fa7b94bbe7e5201ce1c5\",\"ean\":\"4012160121101\",\"correspondingInformationItems\":[{\"itemId\":\"otto.de-785319485\",\"link\":\"https://otto.de/p/785319485\",\"price-current\":19.5,\"price-initial\":19.5,\"title-image\":\"https://i.otto.de/i/otto/30717151?h=520&w=551&sm=clamp\"}],\"title\":\"3DMini Golf Nintendo Switch, Software Pyramide\",\"title-image\":\"https://i.otto.de/i/otto/30717151?h=520&w=551&sm=clamp\",\"navigationPath\":[\"MULTIMEDIA\",\"MULTIMEDIA_GAMES\",\"MULTIMEDIA_GAMES_NINTENDO_SWITCH\"],\"itemId\":\"MULTIMEDIA-MULTIMEDIA_GAMES-MULTIMEDIA_GAMES_NINTENDO_SWITCH-4012160121101\"},{\"_id\":\"5f95fab794bbe7e5201ce1e1\",\"ean\":\"5060528034005\",\"correspondingInformationItems\":[{\"itemId\":\"otto.de-1195302943\",\"link\":\"https://otto.de/p/1195302943\",\"price-current\":39.99,\"price-initial\":39.99,\"title-image\":\"https://i.otto.de/i/otto/986f2b92-43e7-569f-a8d3-0155d6743d2b?h=520&w=551&sm=clamp\"}],\"title\":\"Ben10: Power Trip! Nintendo Switch\",\"title-image\":\"https://i.otto.de/i/otto/986f2b92-43e7-569f-a8d3-0155d6743d2b?h=520&w=551&sm=clamp\",\"navigationPath\":[\"MULTIMEDIA\",\"MULTIMEDIA_GAMES\",\"MULTIMEDIA_GAMES_NINTENDO_SWITCH\"],\"itemId\":\"MULTIMEDIA-MULTIMEDIA_GAMES-MULTIMEDIA_GAMES_NINTENDO_SWITCH-5060528034005\"},{\"_id\":\"5f95fad794bbe7e5201ce1f2\",\"ean\":\"0045496421175\",\"correspondingInformationItems\":[{\"itemId\":\"otto.de-789082145\",\"link\":\"https://otto.de/p/789082145\",\"price-current\":29,\"price-initial\":29,\"title-image\":\"https://i.otto.de/i/otto/21020441?h=520&w=551&sm=clamp\"}],\"title\":\"Snipperclips- Zusammen schneidet man am besten ab! Nintendo Switch\",\"title-image\":\"https://i.otto.de/i/otto/21020441?h=520&w=551&sm=clamp\",\"navigationPath\":[\"MULTIMEDIA\",\"MULTIMEDIA_GAMES\",\"MULTIMEDIA_GAMES_NINTENDO_SWITCH\"],\"itemId\":\"MULTIMEDIA-MULTIMEDIA_GAMES-MULTIMEDIA_GAMES_NINTENDO_SWITCH-0045496421175\"},{\"_id\":\"5f95fae894bbe7e5201ce20f\",\"ean\":\"0045496420383\",\"correspondingInformationItems\":[{\"itemId\":\"otto.de-789082480\",\"link\":\"https://otto.de/p/789082480\",\"price-current\":59,\"price-initial\":59,\"title-image\":\"https://i.otto.de/i/otto/23042987?h=520&w=551&sm=clamp\"},{\"itemId\":\"amazon.de-B01N4OZQWX\",\"link\":\"https://amazon.de/dp/B01N4OZQWX\",\"price-current\":49.99,\"price-initial\":49.99,\"title-image\":\"https://images-na.ssl-images-amazon.com/images/I/71Rqj%2BCh25L._SY679_.jpg\"}],\"title\":\"ARMSNintendo Switch\",\"title-image\":\"https://i.otto.de/i/otto/23042987?h=520&w=551&sm=clamp\",\"navigationPath\":[\"MULTIMEDIA\",\"MULTIMEDIA_GAMES\",\"MULTIMEDIA_GAMES_NINTENDO_SWITCH\"],\"itemId\":\"MULTIMEDIA-MULTIMEDIA_GAMES-MULTIMEDIA_GAMES_NINTENDO_SWITCH-0045496420383\"},{\"_id\":\"5f95fb0494bbe7e5201ce22a\",\"ean\":\"4260558699552\",\"correspondingInformationItems\":[{\"itemId\":\"otto.de-1096998438\",\"link\":\"https://otto.de/p/1096998438\",\"price-current\":38.98,\"price-initial\":38.98,\"title-image\":\"https://i.otto.de/i/otto/0351468a-21fc-5d0c-81c1-c73a5a9c2628?h=520&w=551&sm=clamp\"}],\"title\":\"BubbleBobble 4 Friends Nintendo Switch\",\"title-image\":\"https://i.otto.de/i/otto/0351468a-21fc-5d0c-81c1-c73a5a9c2628?h=520&w=551&sm=clamp\",\"navigationPath\":[\"MULTIMEDIA\",\"MULTIMEDIA_GAMES\",\"MULTIMEDIA_GAMES_NINTENDO_SWITCH\"],\"itemId\":\"MULTIMEDIA-MULTIMEDIA_GAMES-MULTIMEDIA_GAMES_NINTENDO_SWITCH-4260558699552\"}]}"
    }
  },
  {
    "httpRequest": {
      "path": "/api/wishlist-item"
    },
    "httpResponse": {
      "headers": {
        "Content-Type": ["application/json"]
      },
      "body": ""
    }
  }
]




